scanhero/__init__.py
scanhero/cli.py
scanhero/exceptions.py
scanhero/formatters.py
scanhero/models.py
scanhero/scanner.py
scanhero/service_detector.py
scanhero-1.0.0.dist-info/licenses/LICENSE
scanhero-1.0.0.dist-info/METADATA
scanhero-1.0.0.dist-info/WHEEL
scanhero-1.0.0.dist-info/entry_points.txt
scanhero-1.0.0.dist-info/top_level.txt
scanhero-1.0.0.dist-info/RECORD
