Metadata-Version: 2.4
Name: scanhero
Version: 1.0.0
Summary: A modern, lightweight, and modular Python package for basic port and service scanning in cybersecurity contexts
Author-email: Ahmet Hero <ahmet@example.com>
Maintainer-email: Ahmet Hero <ahmet@example.com>
License: MIT
Project-URL: Homepage, https://github.com/ahmetxhero/scanhero
Project-URL: Repository, https://github.com/ahmetxhero/scanhero
Project-URL: Documentation, https://scanhero.readthedocs.io
Project-URL: Bug Tracker, https://github.com/ahmetxhero/scanhero/issues
Keywords: port-scanning,network-security,cybersecurity,asyncio,socket
Classifier: Development Status :: 5 - Production/Stable
Classifier: Intended Audience :: Developers
Classifier: Intended Audience :: System Administrators
Classifier: License :: OSI Approved :: MIT License
Classifier: Operating System :: OS Independent
Classifier: Programming Language :: Python :: 3
Classifier: Programming Language :: Python :: 3.10
Classifier: Programming Language :: Python :: 3.11
Classifier: Programming Language :: Python :: 3.12
Classifier: Programming Language :: Python :: 3.13
Classifier: Topic :: Security
Classifier: Topic :: System :: Networking
Classifier: Topic :: Software Development :: Libraries :: Python Modules
Requires-Python: >=3.10
License-File: LICENSE
Requires-Dist: colorama>=0.4.6
Requires-Dist: rich>=13.0.0
Requires-Dist: aiofiles>=23.0.0
Provides-Extra: dev
Requires-Dist: pytest>=7.0.0; extra == "dev"
Requires-Dist: pytest-asyncio>=0.21.0; extra == "dev"
Requires-Dist: pytest-cov>=4.0.0; extra == "dev"
Requires-Dist: black>=23.0.0; extra == "dev"
Requires-Dist: isort>=5.12.0; extra == "dev"
Requires-Dist: flake8>=6.0.0; extra == "dev"
Requires-Dist: mypy>=1.0.0; extra == "dev"
Requires-Dist: pre-commit>=3.0.0; extra == "dev"
Dynamic: license-file
